lagom/__init__.py
lagom/compilaton.py
lagom/container.py
lagom/context_based.py
lagom/debug.py
lagom/decorators.py
lagom/definitions.py
lagom/environment.py
lagom/exceptions.py
lagom/interfaces.py
lagom/markers.py
lagom/py.typed
lagom/updaters.py
lagom/version.py
lagom/wrapping.py
lagom/experimental/__init__.py
lagom/experimental/context_based.py
lagom/experimental/definitions.py
lagom/experimental/integrations/__init__.py
lagom/experimental/integrations/click.py
lagom/experimental/integrations/django.py
lagom/experimental/integrations/flask.py
lagom/integrations/__init__.py
lagom/integrations/fast_api.py
lagom/integrations/flask.py
lagom/integrations/starlette.py
lagom/util/__init__.py
lagom/util/functional.py
lagom/util/logging.py
lagom/util/reflection.py
lagom-2.7.7.dist-info/licenses/LICENSE
lagom-2.7.7.dist-info/METADATA
lagom-2.7.7.dist-info/WHEEL
lagom-2.7.7.dist-info/top_level.txt
lagom-2.7.7.dist-info/RECORD
