Metadata-Version: 2.4
Name: lagom
Version: 2.7.7
Summary: Lagom is a dependency injection container designed to give you 'just enough' help with building your dependencies.
Author-email: Meadsteve <steve@meadsteve.dev>
License: The MIT License (MIT)
Project-URL: Documentation, https://lagom-di.readthedocs.io/
Project-URL: Changelog, https://lagom-di.readthedocs.io/en/stable/CHANGELOG/
Project-URL: Homepage, https://lagom-di.readthedocs.io/
Project-URL: Github, https://github.com/meadsteve/lagom
Project-URL: Source, https://github.com/meadsteve/lagom
Project-URL: Issues, https://github.com/meadsteve/lagom/issues
Classifier: License :: OSI Approved :: MIT License
Classifier: Programming Language :: Python :: 3.7
Classifier: Programming Language :: Python :: 3.8
Classifier: Programming Language :: Python :: 3.9
Classifier: Programming Language :: Python :: 3.10
Classifier: Programming Language :: Python :: 3.11
Classifier: Programming Language :: Python :: 3.12
Classifier: Programming Language :: Python :: 3.13
Classifier: Topic :: Software Development :: Libraries
Classifier: Typing :: Typed
Requires-Python: >=3.7
License-File: LICENSE
Provides-Extra: env
Requires-Dist: pydantic<3.0.0,>=1.0.0; extra == "env"
Dynamic: license-file
